MANIFEST.in
setup.py
./dali_dataset_op.cc
./dali_tf_plugin_install_tool.py
./dali_tf_plugin_utils.py
./daliop.cc
./setup.py
./stubgen.py
./dali_tf_plugin/dali_dataset.h
./dali_tf_plugin/dali_helper.h
./include/dali/c_api.h
./include/dali/dali.h
./include/dali/dali_cpp_wrappers.h
./include/dali/operators.h
./include/dali/core/access_order.h
./include/dali/core/api_helper.h
./include/dali/core/backend_tags.h
./include/dali/core/bitmask.h
./include/dali/core/boundary.h
./include/dali/core/byte_io.h
./include/dali/core/call_at_exit.h
./include/dali/core/call_once.h
./include/dali/core/common.h
./include/dali/core/convert.h
./include/dali/core/copy_vector_helper.h
./include/dali/core/cuda_error.h
./include/dali/core/cuda_event.h
./include/dali/core/cuda_event_pool.h
./include/dali/core/cuda_rt_utils.h
./include/dali/core/cuda_shared_event.h
./include/dali/core/cuda_stream.h
./include/dali/core/cuda_stream_pool.h
./include/dali/core/cuda_utils.h
./include/dali/core/dali_data_type.h
./include/dali/core/dev_array.h
./include/dali/core/dev_buffer.h
./include/dali/core/dev_string.h
./include/dali/core/device_guard.h
./include/dali/core/dynlink_cuda.h
./include/dali/core/dynlink_cufile.h
./include/dali/core/dynlink_nvcomp.h
./include/dali/core/endian_util.h
./include/dali/core/error_handling.h
./include/dali/core/expand_dims.h
./include/dali/core/fast_div.h
./include/dali/core/float16.h
./include/dali/core/force_inline.h
./include/dali/core/format.h
./include/dali/core/host_dev.h
./include/dali/core/int_literals.h
./include/dali/core/math_util.h
./include/dali/core/nvtx.h
./include/dali/core/partition.h
./include/dali/core/per_stream_pool.h
./include/dali/core/permute.h
./include/dali/core/python_util.h
./include/dali/core/random.h
./include/dali/core/small_vector.h
./include/dali/core/span.h
./include/dali/core/spinlock.h
./include/dali/core/static_map.h
./include/dali/core/static_switch.h
./include/dali/core/stream.h
./include/dali/core/tensor_layout.h
nvidia_dali_tf_plugin_cuda110.egg-info/PKG-INFO
nvidia_dali_tf_plugin_cuda110.egg-info/SOURCES.txt
nvidia_dali_tf_plugin_cuda110.egg-info/dependency_links.txt
nvidia_dali_tf_plugin_cuda110.egg-info/not-zip-safe
nvidia_dali_tf_plugin_cuda110.egg-info/requires.txt
nvidia_dali_tf_plugin_cuda110.egg-info/top_level.txt
