Metadata-Version: 2.4
Name: nvidia-dali-tf-plugin-cuda110
Version: 1.50.0
Summary: NVIDIA DALI  TensorFlow plugin for CUDA 11.0. Git SHA: d5c7b54f776fcba58944048f984f5645e7d7d1bb
Home-page: https://github.com/NVIDIA/dali
Author: NVIDIA Corporation
License: Apache License 2.0
Classifier: Programming Language :: Python :: 3.9
Classifier: Programming Language :: Python :: 3.10
Classifier: Programming Language :: Python :: 3.11
Classifier: Programming Language :: Python :: 3.12
Classifier: Programming Language :: Python :: 3.13
Requires-Python: >=3.9, <3.14
Requires-Dist: nvidia-dali-cuda110==1.50.0
Requires-Dist: packaging
Dynamic: author
Dynamic: classifier
Dynamic: description
Dynamic: description-content-type
Dynamic: home-page
Dynamic: license
Dynamic: requires-dist
Dynamic: requires-python
Dynamic: summary
